imagecompressor/__init__.py
imagecompressor/imagecompressor.py
imagecompressor/modules/__init__.py
imagecompressor/modules/compressors/__init__.py
imagecompressor/modules/compressors/base.py
imagecompressor/modules/compressors/dct.py
imagecompressor/modules/compressors/pil.py
imagecompressor/modules/compressors/raisr.py
imagecompressor/modules/compressors/svd.py
imagecompressor/modules/utils/__init__.py
imagecompressor/modules/utils/io.py
imagecompressor/modules/utils/logger.py
imagecompressor/modules/utils/metrics.py
pyimagecompressor-0.1.1.dist-info/LICENSE
pyimagecompressor-0.1.1.dist-info/METADATA
pyimagecompressor-0.1.1.dist-info/WHEEL
pyimagecompressor-0.1.1.dist-info/top_level.txt
pyimagecompressor-0.1.1.dist-info/zip-safe
pyimagecompressor-0.1.1.dist-info/RECORD
