Metadata-Version: 2.1
Name: pyimagecompressor
Version: 0.1.1
Summary: ImageCompressor: Image compressors written by pure python.
Home-page: https://github.com/CharlesPikachu/imagecompressor
Author: Zhenchao Jin
Author-email: charlesblwx@gmail.com
License: Apache License 2.0
Platform: UNKNOWN
Classifier: License :: OSI Approved :: Apache Software License
Classifier: Programming Language :: Python :: 3
Classifier: Intended Audience :: Developers
Classifier: Operating System :: OS Independent
License-File: LICENSE
Requires-Dist: opencv-python
Requires-Dist: numpy
Requires-Dist: tqdm
Requires-Dist: pillow
Requires-Dist: scipy
